text_normalization/__init__.py
text_normalization/normalization_tools.py
text_normalization/language_variables/__init__.py
text_normalization/language_variables/language_variables.py
text_normalization-0.0.1.dist-info/LICENCE
text_normalization-0.0.1.dist-info/METADATA
text_normalization-0.0.1.dist-info/WHEEL
text_normalization-0.0.1.dist-info/top_level.txt
text_normalization-0.0.1.dist-info/RECORD
