Metadata-Version: 2.1
Name: text-normalization
Version: 0.0.1
Summary: A text normalization package
Home-page: https://github.com/chpalyvos/text-normalization-production
Author: Christos Palyvos
Author-email: chpalyvos@gmail.com
License: UNKNOWN
Platform: UNKNOWN
Classifier: Programming Language :: Python :: 3
Classifier: License :: OSI Approved :: MIT License
Classifier: Operating System :: OS Independent
